OpenFisca_Tracker-0.4.0.dist-info/METADATA
OpenFisca_Tracker-0.4.0.dist-info/RECORD
OpenFisca_Tracker-0.4.0.dist-info/WHEEL
OpenFisca_Tracker-0.4.0.dist-info/top_level.txt
openfisca_tracker/__init__.py
openfisca_tracker/piwik.py
