Metadata-Version: 2.1
Name: OpenFisca-Tracker
Version: 0.4.0
Summary: A Tracker of the OpenFisca Web API usage
Home-page: UNKNOWN
Author: 
License: http://www.fsf.org/licensing/licenses/agpl-3.0.html
Platform: UNKNOWN
Classifier: Programming Language :: Python
Classifier: Programming Language :: Python :: 2.7
Provides-Extra: test
Requires-Dist: grequests (==0.3.0)
Provides-Extra: test
Requires-Dist: nose; extra == 'test'
Requires-Dist: flake8; extra == 'test'
